pyahmia/src/__init__.py
pyahmia/src/_api.py
pyahmia/src/_cache.py
pyahmia/src/_cli.py
pyahmia/src/_lib.py
pyahmia-0.10.0.dist-info/licenses/LICENSE
pyahmia-0.10.0.dist-info/METADATA
pyahmia-0.10.0.dist-info/WHEEL
pyahmia-0.10.0.dist-info/entry_points.txt
pyahmia-0.10.0.dist-info/top_level.txt
pyahmia-0.10.0.dist-info/RECORD
