Metadata-Version: 2.4
Name: pyahmia
Version: 0.10.0
Summary: Search hidden services on the Tor network.
Author-email: Ritchie Mwewa <hi@rly0nheart.com>
License-Expression: MIT
Project-URL: issues, https://codeberg.org/rly0nheart/pyahmia/issues
Project-URL: repository, https://codeberg.org/rly0nheart/pyahmia
Classifier: Development Status :: 5 - Production/Stable
Classifier: Programming Language :: Python :: 3
Classifier: Operating System :: OS Independent
Classifier: Natural Language :: English
Requires-Python: >=3.12
License-File: LICENSE
Requires-Dist: requests-tor>=1.4
Requires-Dist: update-checker>=0.18.0
Requires-Dist: BeautifulSoup4>=4.13.4
Requires-Dist: rich>=13.0.0
Provides-Extra: dev
Requires-Dist: black>=26.1.0; extra == "dev"
Dynamic: license-file
